_kawpow.cp37-win_amd64.pyd
kawpow/__init__.py
kawpow/_build.py
kawpow-0.9.4.4.data/scripts/kawpowhash.py
kawpow-0.9.4.4.dist-info/LICENSE
kawpow-0.9.4.4.dist-info/METADATA
kawpow-0.9.4.4.dist-info/WHEEL
kawpow-0.9.4.4.dist-info/top_level.txt
kawpow-0.9.4.4.dist-info/RECORD
